networking_calico/__init__.py
networking_calico/compat.py
networking_calico/datamodel_v1.py
networking_calico/datamodel_v2.py
networking_calico/datamodel_v3.py
networking_calico/etcdutils.py
networking_calico/etcdv3.py
networking_calico/logutils.py
networking_calico/monotonic.py
networking_calico/timestamp.py
networking_calico/agent/__init__.py
networking_calico/agent/dhcp_agent.py
networking_calico/agent/linux/__init__.py
networking_calico/agent/linux/dhcp.py
networking_calico/agent/linux/interface.py
networking_calico/common/__init__.py
networking_calico/common/config.py
networking_calico/plugins/__init__.py
networking_calico/plugins/calico/__init__.py
networking_calico/plugins/calico/plugin.py
networking_calico/plugins/ml2/__init__.py
networking_calico/plugins/ml2/drivers/__init__.py
networking_calico/plugins/ml2/drivers/calico/__init__.py
networking_calico/plugins/ml2/drivers/calico/election.py
networking_calico/plugins/ml2/drivers/calico/endpoints.py
networking_calico/plugins/ml2/drivers/calico/mech_calico.py
networking_calico/plugins/ml2/drivers/calico/policy.py
networking_calico/plugins/ml2/drivers/calico/status.py
networking_calico/plugins/ml2/drivers/calico/subnets.py
networking_calico/plugins/ml2/drivers/calico/syncer.py
networking_calico/plugins/ml2/drivers/calico/test/__init__.py
networking_calico/plugins/ml2/drivers/calico/test/lib.py
networking_calico/plugins/ml2/drivers/calico/test/stub_etcd.py
networking_calico/plugins/ml2/drivers/calico/test/test_compaction.py
networking_calico/plugins/ml2/drivers/calico/test/test_election.py
networking_calico/plugins/ml2/drivers/calico/test/test_plugin_etcd.py
networking_calico/tests/__init__.py
networking_calico/tests/base.py
networking_calico/tests/py3_test_dhcp_agent.py
networking_calico/tests/py3_test_subnet_watcher.py
networking_calico/tests/test_common.py
networking_calico/tests/test_datamodel_v1.py
networking_calico/tests/test_datamodel_v3.py
networking_calico/tests/test_etcdutils.py
networking_calico-3.12.0.dist-info/AUTHORS
networking_calico-3.12.0.dist-info/LICENSE
networking_calico-3.12.0.dist-info/METADATA
networking_calico-3.12.0.dist-info/WHEEL
networking_calico-3.12.0.dist-info/entry_points.txt
networking_calico-3.12.0.dist-info/pbr.json
networking_calico-3.12.0.dist-info/top_level.txt
networking_calico-3.12.0.dist-info/RECORD
