Metadata-Version: 2.1
Name: networking-calico
Version: 3.12.0
Summary: This project contains documentation and code for integrating Project Calico networking into OpenStack/Neutron.
Home-page: https://docs.openstack.org/networking-calico/latest/
Author: OpenStack
Author-email: openstack-discuss@lists.openstack.org
License: UNKNOWN
Platform: UNKNOWN
Classifier: Environment :: OpenStack
Classifier: Intended Audience :: Information Technology
Classifier: Intended Audience :: System Administrators
Classifier: License :: OSI Approved :: Apache Software License
Classifier: Operating System :: POSIX :: Linux
Classifier: Programming Language :: Python
Classifier: Programming Language :: Python :: 2
Classifier: Programming Language :: Python :: 2.7
Requires-Dist: pbr (>=1.6)
Requires-Dist: Babel (!=2.4.0,>=2.3.4)
Requires-Dist: eventlet (!=0.18.3,!=0.20.1,!=0.21.0,!=0.23.0,>=0.18.2)
Requires-Dist: six (>=1.10.0)
Requires-Dist: etcd3gw (>=0.2.0)
